CHANGELOG
LICENSE
MANIFEST.in
WAIVER
WAIVER.asc
requirements.txt
setup.cfg
setup.py
chainqueue/__init__.py
chainqueue/backend.py
chainqueue/encode.py
chainqueue/entry.py
chainqueue/enum.py
chainqueue/error.py
chainqueue/settings.py
chainqueue/state.py
chainqueue.egg-info/PKG-INFO
chainqueue.egg-info/SOURCES.txt
chainqueue.egg-info/dependency_links.txt
chainqueue.egg-info/entry_points.txt
chainqueue.egg-info/requires.txt
chainqueue.egg-info/top_level.txt
chainqueue/cache/__init__.py
chainqueue/cache/base.py
chainqueue/cache/fs.py
chainqueue/cli/arg.py
chainqueue/cli/config.py
chainqueue/cli/output.py
chainqueue/data/__init__.py
chainqueue/data/config/config.ini
chainqueue/db/__init__.py
chainqueue/db/enum.py
chainqueue/db/migrations/default/README
chainqueue/db/migrations/default/alembic.ini
chainqueue/db/migrations/default/env.py
chainqueue/db/migrations/default/export.py
chainqueue/db/migrations/default/gmon.out
chainqueue/db/migrations/default/script.py.mako
chainqueue/db/migrations/default/versions/2215c497248b_transaction_cache.py
chainqueue/db/migrations/default/versions/3e43847c0717_otx_state_history.py
chainqueue/db/migrations/default/versions/c537a0fd8466_outgoing_queue.py
chainqueue/db/migrations/default/versions/src/otx.py
chainqueue/db/migrations/default/versions/src/otx_state_history.py
chainqueue/db/migrations/default/versions/src/tx_cache.py
chainqueue/db/models/base.py
chainqueue/db/models/otx.py
chainqueue/db/models/state.py
chainqueue/db/models/tx.py
chainqueue/runnable/list.py
chainqueue/runnable/state.py
chainqueue/sql/backend.py
chainqueue/sql/query.py
chainqueue/sql/state.py
chainqueue/sql/tx.py
chainqueue/store/__init__.py
chainqueue/store/base.py
chainqueue/store/fs.py
chainqueue/unittest/db.py